pints/__init__.py
pints/_boundaries.py
pints/_core.py
pints/_diagnostics.py
pints/_error_measures.py
pints/_evaluation.py
pints/_log_likelihoods.py
pints/_log_pdfs.py
pints/_log_priors.py
pints/_logger.py
pints/_sample_initial_points.py
pints/_transformation.py
pints/_util.py
pints/io.py
pints/noise.py
pints/residuals_diagnostics.py
pints/version
pints/_abc/__init__.py
pints/_abc/_abc_rejection.py
pints/_abc/_abc_smc.py
pints/_mcmc/__init__.py
pints/_mcmc/_adaptive_covariance.py
pints/_mcmc/_differential_evolution.py
pints/_mcmc/_dram_ac.py
pints/_mcmc/_dream.py
pints/_mcmc/_dual_averaging.py
pints/_mcmc/_emcee_hammer.py
pints/_mcmc/_haario_ac.py
pints/_mcmc/_haario_bardenet_ac.py
pints/_mcmc/_hamiltonian.py
pints/_mcmc/_mala.py
pints/_mcmc/_metropolis.py
pints/_mcmc/_monomial_gamma_hamiltonian.py
pints/_mcmc/_nuts.py
pints/_mcmc/_population.py
pints/_mcmc/_rao_blackwell_ac.py
pints/_mcmc/_relativistic.py
pints/_mcmc/_slice_doubling.py
pints/_mcmc/_slice_rank_shrinking.py
pints/_mcmc/_slice_stepout.py
pints/_mcmc/_summary.py
pints/_nested/__init__.py
pints/_nested/_ellipsoid.py
pints/_nested/_rejection.py
pints/_optimisers/__init__.py
pints/_optimisers/_adam.py
pints/_optimisers/_cmaes.py
pints/_optimisers/_cmaes_bare.py
pints/_optimisers/_gradient_descent.py
pints/_optimisers/_irpropmin.py
pints/_optimisers/_nelder_mead.py
pints/_optimisers/_pso.py
pints/_optimisers/_snes.py
pints/_optimisers/_xnes.py
pints/interfaces/__init__.py
pints/interfaces/stan/__init__.py
pints/interfaces/stan/_stan.py
pints/plot/__init__.py
pints/plot/_autocorrelation.py
pints/plot/_function.py
pints/plot/_function_between_points.py
pints/plot/_histogram.py
pints/plot/_pairwise.py
pints/plot/_series.py
pints/plot/_surface.py
pints/plot/_trace.py
pints/toy/__init__.py
pints/toy/_annulus.py
pints/toy/_beeler_reuter_model.py
pints/toy/_cone.py
pints/toy/_constant_model.py
pints/toy/_eight_schools.py
pints/toy/_fitzhugh_nagumo_model.py
pints/toy/_gaussian.py
pints/toy/_german_credit.py
pints-0.5.1.dist-info/licenses/LICENSE.md
pints-0.5.1.dist-info/METADATA
pints-0.5.1.dist-info/WHEEL
pints-0.5.1.dist-info/top_level.txt
pints-0.5.1.dist-info/RECORD
