Metadata-Version: 2.4
Name: pints
Version: 0.5.1
Summary: Probabilistic Inference in Noisy Time-Series
Home-page: https://github.com/pints-team/pints
Maintainer: PINTS Team
Maintainer-email: pints@maillist.ox.ac.uk
License: BSD 3-clause license
Project-URL: Bug Tracker, https://github.com/pints-team/pints/issues
Project-URL: Documentation, https://pints.readthedocs.io
Project-URL: Source Code, https://github.com/pints-team/pints
Requires-Python: >=3.8
License-File: LICENSE.md
Requires-Dist: cma>=2
Requires-Dist: numpy>=1.8
Requires-Dist: scipy>=0.14
Requires-Dist: matplotlib>=1.5
Requires-Dist: tabulate
Requires-Dist: threadpoolctl
Provides-Extra: docs
Requires-Dist: sphinx!=1.7.3,>=1.5; extra == "docs"
Provides-Extra: dev
Requires-Dist: flake8>=3; extra == "dev"
Requires-Dist: jupyter; extra == "dev"
Requires-Dist: nbconvert; extra == "dev"
Requires-Dist: traitlets; extra == "dev"
Provides-Extra: stan
Requires-Dist: pystan>=3; extra == "stan"
Dynamic: description
Dynamic: description-content-type
Dynamic: home-page
Dynamic: license
Dynamic: license-file
Dynamic: maintainer
Dynamic: maintainer-email
Dynamic: project-url
Dynamic: provides-extra
Dynamic: requires-dist
Dynamic: requires-python
Dynamic: summary
